octo_pipeline_python/backends/pytest/__init__.py
octo_pipeline_python/backends/pytest/pytest_backend.py
octo_pipeline_python/backends/pytest/actions/__init__.py
octo_pipeline_python/backends/pytest/actions/pytest_e2e_tests.py
octo_pipeline_python/backends/pytest/actions/pytest_integration_tests.py
octo_pipeline_python/backends/pytest/actions/pytest_unit_tests.py
octo_pipeline_python/backends/pytest/models/__init__.py
octo_pipeline_python/backends/pytest/models/pytest_model.py
octo_pipeline_backend_pytest_python-1.3.2.dist-info/LICENSE.txt
octo_pipeline_backend_pytest_python-1.3.2.dist-info/METADATA
octo_pipeline_backend_pytest_python-1.3.2.dist-info/README.md
octo_pipeline_backend_pytest_python-1.3.2.dist-info/WHEEL
octo_pipeline_backend_pytest_python-1.3.2.dist-info/top_level.txt
octo_pipeline_backend_pytest_python-1.3.2.dist-info/RECORD
